some_pd_tools/__init__.py
some_pd_tools/pd_format.py
some_pd_tools/pd_compare/__init__.py
some_pd_tools/pd_compare/_module_compare.py
some_pd_tools/pd_compare/_module_compare_dtypes.py
some_pd_tools/pd_compare/_module_compare_lists.py
some_pd_tools/pd_compare/_module_compute_equality_df.py
some_pd_tools/pd_compare/_module_report_formatting.py
some_pd_tools/tests/__init__.py
some_pd_tools/tests/basedf.py
some_pd_tools/tests/formatting.py
some_pd_tools/tests/pd_compare/__init__.py
some_pd_tools/tests/pd_compare/test_compare.py
some_pd_tools/tests/pd_compare/test_compare_dtypes.py
some_pd_tools/tests/pd_compare/test_compare_lists.py
some_pd_tools/tests/pd_compare/test_compute_equality_df.py
some_pd_tools/tests/pd_format/__init__.py
some_pd_tools/tests/pd_format/test_approximate.py
some_pd_tools/tests/pd_format/test_number_separators.py
some_pd_tools/tests/pd_format/test_obj_as_sorted_list.py
some_pd_tools/tests/pd_format/test_simplify_dtypes.py
some_pd_tools-1.0.3.dist-info/LICENSE
some_pd_tools-1.0.3.dist-info/METADATA
some_pd_tools-1.0.3.dist-info/WHEEL
some_pd_tools-1.0.3.dist-info/top_level.txt
some_pd_tools-1.0.3.dist-info/RECORD
