Metadata-Version: 2.1
Name: some_pd_tools
Version: 1.0.3
Summary: Some tools to be used with Pandas.
Home-page: https://github.com/caballerofelipe/some_pd_tools
Author: Felipe Caballero
License: GPL-3.0
Classifier: License :: OSI Approved :: GNU General Public License v3 (GPLv3)
Classifier: Programming Language :: Python :: 3
Classifier: Operating System :: OS Independent
Requires-Python: >=3.4
License-File: LICENSE
Requires-Dist: pandas >=2
Provides-Extra: dev
Requires-Dist: pytest ; extra == 'dev'
Requires-Dist: twine ; extra == 'dev'
Requires-Dist: build ; extra == 'dev'
